frontend_ui5/__init__.py
frontend_ui5/static/index.html
frontend_ui5/static/manifest.json
frontend_ui5/static/pwa.json
frontend_ui5/static/service-worker.js
frontend_ui5/static/control/MarkdownContent.css
frontend_ui5/static/css/style.css
frontend_ui5/static/i18n/markdown/home_de.md
frontend_ui5/static/i18n/markdown/home_en.md
frontend_ui5/static/i18n/markdown/legal_de.md
frontend_ui5/static/i18n/markdown/legal_en.md
frontend_ui5/static/img/favicon.svg
frontend_ui5/static/img/logo-dark.svg
frontend_ui5/static/img/logo-light.svg
frontend_ui5/static/resources/app.version.json
frontend_ui5/static/resources/sap-ui-custom.js
frontend_ui5/static/resources/sap-ui-version.json
frontend_ui5/static/resources/sap/m/manifest.json
frontend_ui5/static/resources/sap/m/messagebundle_de.properties
frontend_ui5/static/resources/sap/m/messagebundle_en.properties
frontend_ui5/static/resources/sap/m/designtime/messagebundle_de.properties
frontend_ui5/static/resources/sap/m/designtime/messagebundle_en.properties
frontend_ui5/static/resources/sap/m/themes/base/library-parameters.json
frontend_ui5/static/resources/sap/m/themes/base/library.css
frontend_ui5/static/resources/sap/m/themes/sap_horizon/library-parameters.json
frontend_ui5/static/resources/sap/m/themes/sap_horizon/library.css
frontend_ui5/static/resources/sap/m/themes/sap_horizon_dark/library-parameters.json
frontend_ui5/static/resources/sap/m/themes/sap_horizon_dark/library.css
frontend_ui5/static/resources/sap/tnt/manifest.json
frontend_ui5/static/resources/sap/tnt/messagebundle_de.properties
frontend_ui5/static/resources/sap/tnt/messagebundle_en.properties
frontend_ui5/static/resources/sap/tnt/themes/base/library-parameters.json
frontend_ui5/static/resources/sap/tnt/themes/base/library.css
frontend_ui5/static/resources/sap/tnt/themes/base/fonts/SAP-icons-TNT.json
frontend_ui5/static/resources/sap/tnt/themes/base/fonts/SAP-icons-TNT.woff2
frontend_ui5/static/resources/sap/tnt/themes/base/fonts/horizon/SAP-icons-TNT.woff2
frontend_ui5-0.1.27.dist-info/LICENSES-info.txt
frontend_ui5-0.1.27.dist-info/LICENSES.txt
frontend_ui5-0.1.27.dist-info/METADATA
frontend_ui5-0.1.27.dist-info/WHEEL
frontend_ui5-0.1.27.dist-info/top_level.txt
frontend_ui5-0.1.27.dist-info/RECORD
